{
  "__inputs": [],
  "__requires": [],
  "annotations": { "list": [] },
  "description": "HTTP API request rates, latencies, and error rates",
  "editable": true,
  "fiscalYearStartMonth": 0,
  "graphTooltip": 1,
  "id": null,
  "links": [],
  "panels": [
    {
      "datasource": { "type": "prometheus", "uid": "prometheus" },
      "fieldConfig": {
        "defaults": { "color": { "mode": "palette-classic" }, "custom": { "lineWidth": 2 } },
        "overrides": []
      },
      "gridPos": { "h": 8, "w": 12, "x": 0, "y": 0 },
      "id": 1,
      "options": { "legend": { "calcs": ["lastNotNull"], "displayMode": "list", "placement": "bottom" }, "tooltip": { "mode": "multi" } },
      "targets": [
        {
          "expr": "sum(rate(http_requests_total[1m])) by (path, method)",
          "legendFormat": "{{method}} {{path}}",
          "refId": "A"
        }
      ],
      "title": "Request Rate (req/s)",
      "type": "timeseries"
    },
    {
      "datasource": { "type": "prometheus", "uid": "prometheus" },
      "fieldConfig": {
        "defaults": { "color": { "mode": "palette-classic" }, "custom": { "lineWidth": 2 }, "unit": "s" },
        "overrides": []
      },
      "gridPos": { "h": 8, "w": 12, "x": 12, "y": 0 },
      "id": 2,
      "options": { "legend": { "calcs": ["lastNotNull", "mean"], "displayMode": "list", "placement": "bottom" }, "tooltip": { "mode": "multi" } },
      "targets": [
        {
          "expr": "histogram_quantile(0.50, sum(rate(http_request_duration_seconds_bucket[1m])) by (le, path))",
          "legendFormat": "p50 {{path}}",
          "refId": "A"
        },
        {
          "expr": "histogram_quantile(0.95, sum(rate(http_request_duration_seconds_bucket[1m])) by (le, path))",
          "legendFormat": "p95 {{path}}",
          "refId": "B"
        },
        {
          "expr": "histogram_quantile(0.99, sum(rate(http_request_duration_seconds_bucket[1m])) by (le, path))",
          "legendFormat": "p99 {{path}}",
          "refId": "C"
        }
      ],
      "title": "Request Latency (p50 / p95 / p99)",
      "type": "timeseries"
    },
    {
      "datasource": { "type": "prometheus", "uid": "prometheus" },
      "fieldConfig": {
        "defaults": { "color": { "mode": "palette-classic" }, "custom": { "lineWidth": 2 } },
        "overrides": []
      },
      "gridPos": { "h": 8, "w": 12, "x": 0, "y": 8 },
      "id": 3,
      "options": { "legend": { "calcs": ["lastNotNull"], "displayMode": "list", "placement": "bottom" }, "tooltip": { "mode": "multi" } },
      "targets": [
        {
          "expr": "sum(rate(http_requests_total{status=~\"5..\"}[1m])) by (path)",
          "legendFormat": "5xx {{path}}",
          "refId": "A"
        },
        {
          "expr": "sum(rate(http_requests_total{status=~\"4..\"}[1m])) by (path)",
          "legendFormat": "4xx {{path}}",
          "refId": "B"
        }
      ],
      "title": "Error Rate (4xx / 5xx per second)",
      "type": "timeseries"
    },
    {
      "datasource": { "type": "prometheus", "uid": "prometheus" },
      "fieldConfig": {
        "defaults": { "color": { "mode": "thresholds" }, "thresholds": { "mode": "absolute", "steps": [{ "color": "green", "value": null }, { "color": "yellow", "value": 0.01 }, { "color": "red", "value": 0.05 }] }, "unit": "percentunit" },
        "overrides": []
      },
      "gridPos": { "h": 8, "w": 12, "x": 12, "y": 8 },
      "id": 4,
      "options": { "reduceOptions": { "calcs": ["lastNotNull"] }, "orientation": "auto", "textMode": "auto", "colorMode": "background" },
      "targets": [
        {
          "expr": "sum(rate(http_requests_total{status=~\"5..\"}[5m])) / sum(rate(http_requests_total[5m]))",
          "legendFormat": "Error Ratio (5xx)",
          "refId": "A"
        }
      ],
      "title": "5xx Error Ratio (5m window)",
      "type": "stat"
    }
  ],
  "refresh": "10s",
  "schemaVersion": 38,
  "tags": ["search-system", "api"],
  "templating": { "list": [] },
  "time": { "from": "now-1h", "to": "now" },
  "timepicker": {},
  "timezone": "browser",
  "title": "01 — API Overview",
  "uid": "search-api-overview",
  "version": 1
}
